autoannotator/__init__.py
autoannotator/clustering/.gitkeep
autoannotator/clustering/__init__.py
autoannotator/clustering/core/base_clustering.py
autoannotator/clustering/methods/dbscan.py
autoannotator/config/detection.py
autoannotator/config/feature_extraction.py
autoannotator/config/image_alignment.py
autoannotator/custom_ops/__init__.py
autoannotator/custom_ops/custom_ops_mapping.py
autoannotator/custom_ops_storage/.gitkepp
autoannotator/detection/.gitkeep
autoannotator/detection/core/base_detector.py
autoannotator/detection/faces/__init__.py
autoannotator/detection/faces/models/ensemble.py
autoannotator/detection/faces/models/scrfd.py
autoannotator/detection/faces/models/yolov7.py
autoannotator/detection/human/__init__.py
autoannotator/detection/human/models/ensemble.py
autoannotator/detection/human/models/internimage.py
autoannotator/detection/human/models/iter_detr.py
autoannotator/detection/human/models/rtdetr.py
autoannotator/detection/human/models/uhihcp.py
autoannotator/detection/utils/wbf.py
autoannotator/feature_extraction/__init__.py
autoannotator/feature_extraction/core/feature_extractor.py
autoannotator/feature_extraction/faces/__init__.py
autoannotator/feature_extraction/faces/models/__init__.py
autoannotator/feature_extraction/faces/models/ensemble.py
autoannotator/feature_extraction/faces/models/face_feature_extractor.py
autoannotator/feature_extraction/faces/models/model_adaface.py
autoannotator/feature_extraction/faces/models/model_insightface.py
autoannotator/types/base.py
autoannotator/types/custom_typing.py
autoannotator/types/faces.py
autoannotator/utils/.gitkeep
autoannotator/utils/algorithms.py
autoannotator/utils/image_alignment.py
autoannotator/utils/image_preprocessing.py
autoannotator/utils/image_reader.py
autoannotator/utils/image_visualization.py
autoannotator/utils/misc.py
autoannotator/utils/onnx_model_handler.py
autoannotator/weights/detection/.gitkeep
autoannotator/weights/detection/faces/.gitkeep
autoannotator-0.2.0.dist-info/METADATA
autoannotator-0.2.0.dist-info/WHEEL
autoannotator-0.2.0.dist-info/licenses/LICENSE
autoannotator-0.2.0.dist-info/RECORD
