Metadata-Version: 2.1
Name: autoannotator
Version: 0.2.0
Summary: Automatic annotation of images library
Project-URL: Homepage, https://github.com/CatsWhoTrain/autoannotator
Project-URL: Bug Tracker, https://github.com/CatsWhoTrain/autoannotator/issues
Author-email: Alexander FIlonenko <alexander@filonenko.net>, Igor Popov <ig.popov1997@gmail.com>, Roman Savoskin <xromndev@gmail.com>
License-File: LICENSE
Classifier: Operating System :: OS Independent
Classifier: Programming Language :: Python :: 3
Requires-Python: >=3.10
Requires-Dist: loguru
Requires-Dist: onnx
Requires-Dist: onnxruntime-gpu
Requires-Dist: opencv-python
Requires-Dist: pydantic
Requires-Dist: pytest
Requires-Dist: requests
Requires-Dist: scikit-image
Requires-Dist: scikit-learn
Requires-Dist: tqdm
